zemia/__init__.py
zemia/common.py
zemia/file.py
zemia/spreadsheet.py
zemia/sql.py
zemia-0.1.0.dist-info/METADATA
zemia-0.1.0.dist-info/WHEEL
zemia-0.1.0.dist-info/licenses/LICENSE
zemia-0.1.0.dist-info/RECORD
